LICENSE
README.md
pyproject.toml
setup.py
NNS/Binary_ANOVA.py
NNS/Copula.py
NNS/FSD.py
NNS/Internal_Functions.py
NNS/LPM_UPM_VaR.py
NNS/NNS_term_matrix.py
NNS/Numerical_Differentiation.py
NNS/Partial_Moments.py
NNS/SD_Efficient_Set.py
NNS/SSD.py
NNS/TSD.py
NNS/Uni_SD_Routines.py
NNS/__init__.py
NNS.egg-info/PKG-INFO
NNS.egg-info/SOURCES.txt
NNS.egg-info/dependency_links.txt
NNS.egg-info/requires.txt
NNS.egg-info/top_level.txt
tests/__init__.py
tests/main.py
tests/unit/__init__.py