Metadata-Version: 2.1
Name: NNS
Version: 0.1.13
Summary: Nonlinear nonparametric statistics using partial moments
Home-page: https://github.com/OVVO-Financial/NNS-Python/
Author: Fred Viole, Roberto Spadim
Author-email: ovvo.financial.systems@gmail.com
License: UNKNOWN
Download-URL: https://github.com/OVVO-Financial/NNS-Python/archive/refs/tags/v_0113.tar.gz
Keywords: Nonlinear nonparametric regression classification clustering
Platform: UNKNOWN
Classifier: Development Status :: 3 - Alpha
Classifier: Programming Language :: Python :: 3.8
Classifier: Programming Language :: Python :: 3.7
Requires-Python: >=3.7
Provides-Extra: test
Provides-Extra: plot
License-File: LICENSE
